rag_tui/__init__.py
rag_tui/__main__.py
rag_tui/app.py
rag_tui/core/__init__.py
rag_tui/core/engine.py
rag_tui/core/file_handler.py
rag_tui/core/llm.py
rag_tui/core/metrics.py
rag_tui/core/presets.py
rag_tui/core/providers.py
rag_tui/core/strategies.py
rag_tui/core/vector.py
rag_tui/styles/app.tcss
rag_tui/widgets/__init__.py
rag_tui/widgets/chunk_card.py
rag_tui/widgets/control_bar.py
rag_tui/widgets/help_overlay.py
rag_tui/widgets/parameter_panel.py
rag_tui/widgets/search_panel.py
rag_tui-0.0.3b1.dist-info/METADATA
rag_tui-0.0.3b1.dist-info/WHEEL
rag_tui-0.0.3b1.dist-info/entry_points.txt
rag_tui-0.0.3b1.dist-info/licenses/LICENSE
rag_tui-0.0.3b1.dist-info/RECORD
