Metadata-Version: 2.4
Name: rag-tui
Version: 0.0.3b1
Summary: Interactive terminal UI for visualizing, debugging, and tuning RAG chunking pipelines
Project-URL: Homepage, https://github.com/rasinmuhammed/rag-tui
Project-URL: Documentation, https://github.com/rasinmuhammed/rag-tui#readme
Project-URL: Repository, https://github.com/rasinmuhammed/rag-tui
Project-URL: Issues, https://github.com/rasinmuhammed/rag-tui/issues
Author-email: Muhammed Rasin <rasinbinabdulla@gmail.com>
License: MIT
License-File: LICENSE
Keywords: chunking,debugging,embeddings,llm,rag,retrieval-augmented-generation,terminal,textual,tui,vector-search
Classifier: Development Status :: 4 - Beta
Classifier: Environment :: Console
Classifier: Intended Audience :: Developers
Classifier: License :: OSI Approved :: MIT License
Classifier: Operating System :: OS Independent
Classifier: Programming Language :: Python :: 3
Classifier: Programming Language :: Python :: 3.10
Classifier: Programming Language :: Python :: 3.11
Classifier: Programming Language :: Python :: 3.12
Classifier: Topic :: Scientific/Engineering :: Artificial Intelligence
Classifier: Topic :: Software Development :: Debuggers
Classifier: Topic :: Text Processing :: General
Requires-Python: >=3.10
Requires-Dist: chonkie>=0.1.0
Requires-Dist: httpx>=0.25.0
Requires-Dist: numpy>=1.24.0
Requires-Dist: ollama>=0.1.0
Requires-Dist: pypdf>=3.0.0
Requires-Dist: pyyaml>=6.0.0
Requires-Dist: rich>=13.0.0
Requires-Dist: textual>=0.40.0
Requires-Dist: usearch>=2.0.0
Provides-Extra: dev
Requires-Dist: pytest-asyncio>=0.21.0; extra == 'dev'
Requires-Dist: pytest>=7.0.0; extra == 'dev'
